[
    { "x": 1, "y": 1, "borders": ["top", "left"] },
    { "x": 2, "y": 1, "borders": ["top"] },
    { "x": 3, "y": 1, "borders": ["top"] },
    { "x": 4, "y": 1, "borders": ["top"] },
    { "x": 5, "y": 1, "borders": ["top", "left"] },
    { "x": 6, "y": 1, "borders": ["top"] },
    { "x": 7, "y": 1, "borders": ["top"] },
    { "x": 8, "y": 1, "borders": ["top"] },
    { "x": 9, "y": 1, "borders": ["top", "left"] },
    { "x": 10, "y": 1, "borders": ["top"] },
    { "x": 11, "y": 1, "borders": ["top"] },
    { "x": 12, "y": 1, "borders": ["left"] },
    { "x": 1, "y": 2, "borders": ["left"] },
    { "x": 5, "y": 2, "borders": ["left"] },
    { "x": 9, "y": 2, "borders": ["left"] },
    { "x": 12, "y": 2, "borders": ["left"] },
    { "x": 1, "y": 3, "borders": ["left"] },
    { "x": 5, "y": 3, "borders": ["left"] },
    { "x": 9, "y": 3, "borders": ["left"] },
    { "x": 12, "y": 3, "borders": ["left"] },
    { "x": 1, "y": 4, "borders": ["top", "left"] },
    { "x": 2, "y": 4, "borders": ["top"] },
    { "x": 3, "y": 4, "borders": ["top"] },
    { "x": 4, "y": 4, "borders": ["top"] },
    { "x": 5, "y": 4, "borders": ["top", "left"] },
    { "x": 6, "y": 4, "borders": ["top"] },
    { "x": 7, "y": 4, "borders": ["top"] },
    { "x": 8, "y": 4, "borders": ["top"] },
    { "x": 9, "y": 4, "borders": ["left"] },
    { "x": 12, "y": 4, "borders": ["left"] },
    { "x": 1, "y": 5, "borders": ["left"] },
    { "x": 5, "y": 5, "borders": ["left"] },
    { "x": 9, "y": 5, "borders": ["left"] },
    { "x": 12, "y": 5, "borders": ["left"] },
    { "x": 1, "y": 6, "borders": ["left"] },
    { "x": 5, "y": 6, "borders": ["left"] },
    { "x": 9, "y": 6, "borders": ["top", "left"] },
    { "x": 10, "y": 6, "borders": ["top"] },
    { "x": 11, "y": 6, "borders": ["top"] },
    { "x": 1, "y": 7, "borders": ["left"] },
    { "x": 5, "y": 7, "borders": ["left"] },
    { "x": 9, "y": 7, "borders": ["left"] },
    { "x": 1, "y": 8, "borders": ["left"] },
    { "x": 5, "y": 8, "borders": ["left"] },
    { "x": 9, "y": 8, "borders": ["left"] },
    { "x": 1, "y": 9, "borders": ["top"] },
    { "x": 2, "y": 9, "borders": ["top"] },
    { "x": 3, "y": 9, "borders": ["top"] },
    { "x": 4, "y": 9, "borders": ["top"] },
    { "x": 5, "y": 9, "borders": ["top"] },
    { "x": 6, "y": 9, "borders": ["top"] },
    { "x": 7, "y": 9, "borders": ["top"] },
    { "x": 8, "y": 9, "borders": ["top"] },
    
    { "x": 14, "y": 1, "borders": ["top", "left"] },
    { "x": 15, "y": 1, "borders": ["top"] },
    { "x": 16, "y": 1, "borders": ["top"] },
    { "x": 17, "y": 1, "borders": ["top", "left"] },
    { "x": 18, "y": 1, "borders": ["top"] },
    { "x": 19, "y": 1, "borders": ["top"] },
    { "x": 20, "y": 1, "borders": ["top"] },
    { "x": 21, "y": 1, "borders": ["top", "left"] },
    { "x": 22, "y": 1, "borders": ["top"] },
    { "x": 23, "y": 1, "borders": ["top"] },
    { "x": 24, "y": 1, "borders": ["top"] },
    { "x": 25, "y": 1, "borders": ["left"] },
    { "x": 14, "y": 2, "borders": ["left"] },
    { "x": 17, "y": 2, "borders": ["left"] },
    { "x": 21, "y": 2, "borders": ["left"] },
    { "x": 25, "y": 2, "borders": ["left"] },
    { "x": 14, "y": 3, "borders": ["left"] },
    { "x": 17, "y": 3, "borders": ["left"] },
    { "x": 21, "y": 3, "borders": ["left"] },
    { "x": 25, "y": 3, "borders": ["left"] },
    { "x": 14, "y": 4, "borders": ["left"] },
    { "x": 17, "y": 4, "borders": ["left"] },
    { "x": 21, "y": 4, "borders": ["left"] },
    { "x": 25, "y": 4, "borders": ["left"] },
    { "x": 14, "y": 5, "borders": ["left"] },
    { "x": 17, "y": 5, "borders": ["top", "left"] },
    { "x": 18, "y": 5, "borders": ["top"] },
    { "x": 19, "y": 5, "borders": ["top"] },
    { "x": 20, "y": 5, "borders": ["top"] },
    { "x": 21, "y": 5, "borders": ["top", "left"] },
    { "x": 22, "y": 5, "borders": ["top"] },
    { "x": 23, "y": 5, "borders": ["top"] },
    { "x": 24, "y": 5, "borders": ["top"] },
    { "x": 25, "y": 5, "borders": ["left"] },
    { "x": 14, "y": 6, "borders": ["top"] },
    { "x": 15, "y": 6, "borders": ["top"] },
    { "x": 16, "y": 6, "borders": ["top"] },
    { "x": 17, "y": 6, "borders": ["left"] },
    { "x": 21, "y": 6, "borders": ["left"] },
    { "x": 25, "y": 6, "borders": ["left"] },
    { "x": 17, "y": 7, "borders": ["left"] },
    { "x": 21, "y": 7, "borders": ["left"] },
    { "x": 25, "y": 7, "borders": ["left"] },
    { "x": 17, "y": 8, "borders": ["left"] },
    { "x": 21, "y": 8, "borders": ["left"] },
    { "x": 25, "y": 8, "borders": ["left"] },
    { "x": 17, "y": 9, "borders": ["top"] },
    { "x": 18, "y": 9, "borders": ["top"] },
    { "x": 19, "y": 9, "borders": ["top"] },
    { "x": 20, "y": 9, "borders": ["top"] },
    { "x": 21, "y": 9, "borders": ["top"] },
    { "x": 22, "y": 9, "borders": ["top"] },
    { "x": 23, "y": 9, "borders": ["top"] },
    { "x": 24, "y": 9, "borders": ["top"] },

    { "x": 1, "y": 10, "borders": ["top", "left"] },
    { "x": 2, "y": 10, "borders": ["top"] },
    { "x": 3, "y": 10, "borders": ["top"] },
    { "x": 4, "y": 10, "borders": ["top"] },
    { "x": 5, "y": 10, "borders": ["top", "left"] },
    { "x": 6, "y": 10, "borders": ["top"] },
    { "x": 7, "y": 10, "borders": ["top", "left"] },
    { "x": 8, "y": 10, "borders": ["top"] },
    { "x": 9, "y": 10, "borders": ["left"] },
    { "x": 1, "y": 11, "borders": ["left"] },
    { "x": 5, "y": 11, "borders": ["left"] },
    { "x": 7, "y": 11, "borders": ["left"] },
    { "x": 9, "y": 11, "borders": ["left"] },
    { "x": 1, "y": 12, "borders": ["left"] },
    { "x": 5, "y": 12, "borders": ["left"] },
    { "x": 7, "y": 12, "borders": ["left"] },
    { "x": 9, "y": 12, "borders": ["left"] },
    { "x": 1, "y": 13, "borders": ["left"] },
    { "x": 5, "y": 13, "borders": ["top", "left"] },
    { "x": 6, "y": 13, "borders": ["top"] },
    { "x": 7, "y": 13, "borders": ["top"] },
    { "x": 8, "y": 13, "borders": ["top"] },
    { "x": 9, "y": 13, "borders": ["top", "left"] },
    { "x": 10, "y": 13, "borders": ["top"] },
    { "x": 11, "y": 13, "borders": ["top"] },
    { "x": 12, "y": 13, "borders": ["left"] },
    { "x": 1, "y": 14, "borders": ["top", "left"] },
    { "x": 2, "y": 14, "borders": ["top"] },
    { "x": 3, "y": 14, "borders": ["top"] },
    { "x": 4, "y": 14, "borders": ["top"] },
    { "x": 5, "y": 14, "borders": ["left"] },
    { "x": 9, "y": 14, "borders": ["left"] },
    { "x": 12, "y": 14, "borders": ["left"] },
    { "x": 1, "y": 15, "borders": ["left"] },
    { "x": 5, "y": 15, "borders": ["left"] },
    { "x": 9, "y": 15, "borders": ["left"] },
    { "x": 12, "y": 15, "borders": ["left"] },
    { "x": 1, "y": 16, "borders": ["left"] },
    { "x": 5, "y": 16, "borders": ["left"] },
    { "x": 9, "y": 16, "borders": ["left"] },
    { "x": 12, "y": 16, "borders": ["left"] },
    { "x": 1, "y": 17, "borders": ["left"] },
    { "x": 5, "y": 17, "borders": ["left"] },
    { "x": 9, "y": 17, "borders": ["left"] },
    { "x": 12, "y": 17, "borders": ["left"] },
    { "x": 1, "y": 18, "borders": ["top"] },
    { "x": 2, "y": 18, "borders": ["top"] },
    { "x": 3, "y": 18, "borders": ["top"] },
    { "x": 4, "y": 18, "borders": ["top"] },
    { "x": 5, "y": 18, "borders": ["top"] },
    { "x": 6, "y": 18, "borders": ["top"] },
    { "x": 7, "y": 18, "borders": ["top"] },
    { "x": 8, "y": 18, "borders": ["top"] },
    { "x": 9, "y": 18, "borders": ["top"] },
    { "x": 10, "y": 18, "borders": ["top"] },
    { "x": 11, "y": 18, "borders": ["top"] },
    
    { "x": 17, "y": 10, "borders": ["top", "left"] },
    { "x": 18, "y": 10, "borders": ["top"] },
    { "x": 19, "y": 10, "borders": ["top"] },
    { "x": 20, "y": 10, "borders": ["top"] },
    { "x": 21, "y": 10, "borders": ["top", "left"] },
    { "x": 22, "y": 10, "borders": ["top"] },
    { "x": 23, "y": 10, "borders": ["top"] },
    { "x": 24, "y": 10, "borders": ["top"] },
    { "x": 25, "y": 10, "borders": ["left"] },
    { "x": 17, "y": 11, "borders": ["left"] },
    { "x": 21, "y": 11, "borders": ["left"] },
    { "x": 25, "y": 11, "borders": ["left"] },
    { "x": 17, "y": 12, "borders": ["left"] },
    { "x": 21, "y": 12, "borders": ["left"] },
    { "x": 25, "y": 12, "borders": ["left"] },
    { "x": 14, "y": 13, "borders": ["top", "left"] },
    { "x": 15, "y": 13, "borders": ["top"] },
    { "x": 16, "y": 13, "borders": ["top"] },
    { "x": 17, "y": 13, "borders": ["top"] },
    { "x": 18, "y": 13, "borders": ["left"] },
    { "x": 21, "y": 13, "borders": ["left"] },
    { "x": 25, "y": 13, "borders": ["left"] },
    { "x": 14, "y": 14, "borders": ["left"] },
    { "x": 18, "y": 14, "borders": ["top", "left"] },
    { "x": 19, "y": 14, "borders": ["top"] },
    { "x": 20, "y": 14, "borders": ["top"] },
    { "x": 21, "y": 14, "borders": ["top", "left"] },
    { "x": 22, "y": 14, "borders": ["top"] },
    { "x": 23, "y": 14, "borders": ["top"] },
    { "x": 24, "y": 14, "borders": ["top"] },
    { "x": 25, "y": 14, "borders": ["left"] },
    { "x": 14, "y": 15, "borders": ["left"] },
    { "x": 18, "y": 15, "borders": ["left"] },
    { "x": 21, "y": 15, "borders": ["left"] },
    { "x": 25, "y": 15, "borders": ["left"] },
    { "x": 14, "y": 16, "borders": ["left"] },
    { "x": 18, "y": 16, "borders": ["left"] },
    { "x": 21, "y": 16, "borders": ["left"] },
    { "x": 25, "y": 16, "borders": ["left"] },
    { "x": 14, "y": 17, "borders": ["left"] },
    { "x": 18, "y": 17, "borders": ["left"] },
    { "x": 21, "y": 17, "borders": ["left"] },
    { "x": 25, "y": 17, "borders": ["left"] },
    { "x": 14, "y": 18, "borders": ["top"] },
    { "x": 15, "y": 18, "borders": ["top"] },
    { "x": 16, "y": 18, "borders": ["top"] },
    { "x": 17, "y": 18, "borders": ["top"] },
    { "x": 18, "y": 18, "borders": ["top"] },
    { "x": 19, "y": 18, "borders": ["top"] },
    { "x": 20, "y": 18, "borders": ["top"] },
    { "x": 21, "y": 18, "borders": ["top"] },
    { "x": 22, "y": 18, "borders": ["top"] },
    { "x": 23, "y": 18, "borders": ["top"] },
    { "x": 24, "y": 18, "borders": ["top"] },

    { "x": 10, "y": 7, "borders": ["top", "left"] },
    { "x": 11, "y": 7, "borders": ["top"] },
    { "x": 12, "y": 7, "borders": ["top"] },
    { "x": 13, "y": 7, "borders": ["top"] },
    { "x": 14, "y": 7, "borders": ["top"] },
    { "x": 15, "y": 7, "borders": ["top"] },
    { "x": 16, "y": 7, "borders": ["left"] },
    { "x": 10, "y": 8, "borders": ["left"] },
    { "x": 16, "y": 8, "borders": ["left"] },
    { "x": 10, "y": 9, "borders": ["left"] },
    { "x": 16, "y": 9, "borders": ["left"] },
    { "x": 10, "y": 10, "borders": ["left"] },
    { "x": 16, "y": 10, "borders": ["left"] },
    { "x": 10, "y": 11, "borders": ["left"] },
    { "x": 16, "y": 11, "borders": ["left"] },
    { "x": 10, "y": 12, "borders": ["top"] },
    { "x": 11, "y": 12, "borders": ["top"] },
    { "x": 12, "y": 12, "borders": ["top"] },
    { "x": 13, "y": 12, "borders": ["top"] },
    { "x": 14, "y": 12, "borders": ["top"] },
    { "x": 15, "y": 12, "borders": ["top"] }
]